[
  {
    "timestamp": 1776970515.85544,
    "duration_seconds": 1868.8928334000084,
    "total_cells": 230400,
    "filled_cells": 230400,
    "columns": 640,
    "rows": 360,
    "palette_size": 3929,
    "emoji_size": 20,
    "emoji_source": "twemoji"
  },
  {
    "timestamp": 1776975849.9037087,
    "duration_seconds": 134.13193960000353,
    "total_cells": 36672,
    "filled_cells": 36672,
    "columns": 192,
    "rows": 191,
    "palette_size": 3921,
    "emoji_size": 20,
    "emoji_source": "twemoji"
  },
  {
    "timestamp": 1776976253.344284,
    "duration_seconds": 308.6426819999906,
    "total_cells": 159200,
    "filled_cells": 159200,
    "columns": 400,
    "rows": 398,
    "palette_size": 3921,
    "emoji_size": 20,
    "emoji_source": "twemoji"
  },
  {
    "timestamp": 1776976697.0262632,
    "duration_seconds": 15.820295099998475,
    "total_cells": 35250,
    "filled_cells": 35250,
    "columns": 250,
    "rows": 141,
    "palette_size": 3921,
    "emoji_size": 20,
    "emoji_source": "twemoji"
  },
  {
    "timestamp": 1776977608.7399807,
    "duration_seconds": 50.174920299992664,
    "total_cells": 83250,
    "filled_cells": 83250,
    "columns": 250,
    "rows": 333,
    "palette_size": 3921,
    "emoji_size": 20,
    "emoji_source": "twemoji"
  },
  {
    "timestamp": 1776977711.5504146,
    "duration_seconds": 21.486073200008832,
    "total_cells": 83250,
    "filled_cells": 83250,
    "columns": 250,
    "rows": 333,
    "palette_size": 3921,
    "emoji_size": 20,
    "emoji_source": "twemoji"
  }
]